hackedit
pytest_hackedit
