Metadata-Version: 1.1
Name: hackedit
Version: 1.0a2
Summary: The hackable IDE, built with Python3, PyQt5 and pyQode
Home-page: https://github.com/HackEdit/hackedit
Author: Colin Duquesnoy
Author-email: colin.duquesnoy@gmail.com
License: GPL
Keywords: IDE,Intergrated Development Environment,TextEditor,Editor
Platform: UNKNOWN
Classifier: Development Status :: 3 - Alpha
Classifier: Environment :: X11 Applications :: Qt
Classifier: Environment :: Win32 (MS Windows)
Classifier: Environment :: MacOS X
Classifier: Intended Audience :: Developers
Classifier: Intended Audience :: Education
Classifier: License :: OSI Approved :: GNU General Public License v2 (GPLv2)
Classifier: Operating System :: Microsoft :: Windows
Classifier: Operating System :: POSIX :: Linux
Classifier: Operating System :: MacOS :: MacOS X
Classifier: Programming Language :: Python :: 3.4
Classifier: Programming Language :: Python :: 3.5
Classifier: Topic :: Software Development
Classifier: Topic :: Text Editors :: Integrated Development Environments (IDE)
